<templateSet group="Sweetchuck - Drupal-10 Core">
    <template name="drupal_cache_bin_service"
              description=""
              toReformat="false"
              toShortenFQNames="true">
        <variable name="name"
                  expression="firstWord(spaceSeparated(fileName()))"
                  defaultValue=""
                  alwaysStopAt="true" />
        <context>
            <option name="CSS"
                    value="false" />
            <option name="CUCUMBER_FEATURE_FILE"
                    value="false" />
            <option name="HTML"
                    value="false" />
            <option name="HTTP_CLIENT_ENVIRONMENT"
                    value="false" />
            <option name="Handlebars"
                    value="false" />
            <option name="JAVA_SCRIPT"
                    value="false" />
            <option name="JSON"
                    value="false" />
            <option name="OTHER"
                    value="true" />
            <option name="PHP"
                    value="false" />
            <option name="REQUEST"
                    value="false" />
            <option name="SHELL_SCRIPT"
                    value="false" />
            <option name="SQL"
                    value="false" />
            <option name="Twig"
                    value="false" />
            <option name="TypeScript"
                    value="false" />
            <option name="Vue"
                    value="false" />
            <option name="XML"
                    value="false" />
        </context>
        <value>
<![CDATA[
cache.$name$:
  class: 'Drupal\Core\Cache\CacheBackendInterface'
  factory:
    - '@cache_factory'
    - 'get'
  arguments:
    - '$name$'
  tags:
    -
      name: 'cache.bin'
      default_backend: 'cache.backend.chainedfast'
$END$
]]>
        </value>
    </template>
    <template name="drupal_logger_channel_service_definition"
              description=""
              toReformat="false"
              toShortenFQNames="true">
        <variable name="module"
                  expression="substringBefore(fileName(), &quot;.&quot;)"
                  defaultValue=""
                  alwaysStopAt="true" />
        <variable name="name"
                  expression=""
                  defaultValue="&quot;foo&quot;"
                  alwaysStopAt="true" />
        <context>
            <option name="CSS"
                    value="false" />
            <option name="CUCUMBER_FEATURE_FILE"
                    value="false" />
            <option name="HTML"
                    value="false" />
            <option name="HTTP_CLIENT_ENVIRONMENT"
                    value="false" />
            <option name="Handlebars"
                    value="false" />
            <option name="JAVA_SCRIPT"
                    value="false" />
            <option name="JSON"
                    value="false" />
            <option name="OTHER"
                    value="true" />
            <option name="PHP"
                    value="false" />
            <option name="REQUEST"
                    value="false" />
            <option name="SHELL_SCRIPT"
                    value="false" />
            <option name="SQL"
                    value="false" />
            <option name="Twig"
                    value="false" />
            <option name="TypeScript"
                    value="false" />
            <option name="Vue"
                    value="false" />
            <option name="XML"
                    value="false" />
        </context>
        <value>
<![CDATA[
logger.channel.$module$_$name$:
  parent: 'logger.channel_base'
  arguments:
    - '$module$_$name$'$END$
]]>
        </value>
    </template>
    <template name="repo_package_drupal"
              description=""
              toReformat="true"
              toShortenFQNames="true">
        <variable name="vendor"
                  expression=""
                  defaultValue="&quot;drupal&quot;"
                  alwaysStopAt="true" />
        <variable name="name"
                  expression=""
                  defaultValue="&quot;bar&quot;"
                  alwaysStopAt="true" />
        <variable name="packageType"
                  expression="enum(&quot;module&quot;, &quot;theme&quot;, &quot;profile&quot;)"
                  defaultValue=""
                  alwaysStopAt="true" />
        <variable name="reference"
                  expression="enum(&quot;8.x-1.x&quot;, &quot;1.x&quot;, &quot;2.x&quot;)"
                  defaultValue=""
                  alwaysStopAt="true" />
        <variable name="distType"
                  expression="enum(&quot;zip&quot;, &quot;tar.gz&quot;)"
                  defaultValue=""
                  alwaysStopAt="true" />
        <variable name="terminator"
                  expression="enum(&quot;,&quot;, &quot;&quot;)"
                  defaultValue=""
                  alwaysStopAt="true" />
        <context>
            <option name="JSON"
                    value="true" />
        </context>
        <value>
<![CDATA[
"$vendor$/$name$": {
    "type": "package",
    "package": {
        "type": "drupal-$packageType$",
        "name": "drupal/$name$",
        "version": "1.0.0",
        "source": {
            "type": "git",
            "reference": "$reference$",
            "url": "https://git.drupalcode.org/project/$name$.git"
        },
        "dist": {
            "type": "$distType$",
            "url": "https://ftp.drupal.org/files/projects/$name$-$reference$-dev.$distType$"
        }
    }
}$terminator$
]]>
        </value>
    </template>
</templateSet>
